atomchain/__init__.py
atomchain/frozenphonon.py
atomchain/gap.py
atomchain/init_model.py
atomchain/mlphonon.py
atomchain/mlpot.py
atomchain/relax.py
atomchain-0.1.1.dist-info/METADATA
atomchain-0.1.1.dist-info/WHEEL
atomchain-0.1.1.dist-info/entry_points.txt
atomchain-0.1.1.dist-info/top_level.txt
atomchain-0.1.1.dist-info/RECORD
